{
  "bookId": 21,
  "title": "Empire of Pain",
  "subtitle": "The Secret History of the Sackler Dynasty",
  "authors": [
    "Patrick Radden Keefe"
  ],
  "topic": "Current Events & People",
  "fiction": false,
  "publicationYear": 2021,
  "pageCount": 720,
  "isbn13": "9780385545686",
  "olKey": "/works/OL24218388W",
  "synopsis": null,
  "picker": [
    "loren"
  ],
  "subjects": [
    "Biographies",
    "Pharmaceutical industry",
    "Corrupt practices",
    "drugs",
    "marketing",
    "philanthropists",
    "Oxycodone",
    "Oxycodone abuse",
    "Purdue Pharma L.P.",
    "Biography",
    "Biography & Memoir",
    "Business"
  ]
}
